{
  "product_code": "91337",
  "name": "Chicken Bacon Ranch Street Chalupas",
  "description": "",
  "category": "specialties",
  "image_url": "https://www.tacobell.com/images/27057_chicken_bacon_ranch_street_chalupas_269x269.jpg",
  "is_vegetarian": false,
  "is_meatless": false,
  "first_seen_at": "2026-03-23T03:56:06.702421+00:00",
  "availability_pct": 0.6,
  "price_stats": {
    "avg": 6.27,
    "min": 5.99,
    "max": 6.99,
    "median": 5.99,
    "std_dev": 0.36,
    "store_count": 46
  },
  "histogram": [
    {
      "bucket": "$5.99",
      "count": 26
    },
    {
      "bucket": "$6.49",
      "count": 13
    },
    {
      "bucket": "$6.79",
      "count": 2
    },
    {
      "bucket": "$6.99",
      "count": 5
    }
  ],
  "state_prices": [
    {
      "state": "TN",
      "avg_price": 6.4,
      "store_count": 11
    },
    {
      "state": "GA",
      "avg_price": 6.37,
      "store_count": 20
    },
    {
      "state": "AL",
      "avg_price": 6.06,
      "store_count": 14
    }
  ],
  "nutrition": null,
  "cheapest_stores": [
    {
      "store_number": "041154",
      "name": "Taco Bell",
      "city": "Columbus",
      "state": "GA",
      "price": 5.99
    },
    {
      "store_number": "042584",
      "name": "Taco Bell",
      "city": "McDonough",
      "state": "GA",
      "price": 5.99
    },
    {
      "store_number": "035455",
      "name": "Taco Bell",
      "city": "Pinson",
      "state": "AL",
      "price": 5.99
    },
    {
      "store_number": "042128",
      "name": "Taco Bell",
      "city": "Chipley",
      "state": "FL",
      "price": 5.99
    },
    {
      "store_number": "030177",
      "name": "Taco Bell",
      "city": "Eufaula",
      "state": "AL",
      "price": 5.99
    },
    {
      "store_number": "042488",
      "name": "Taco Bell",
      "city": "Cookeville",
      "state": "TN",
      "price": 5.99
    },
    {
      "store_number": "037008",
      "name": "Taco Bell",
      "city": "Hoover",
      "state": "AL",
      "price": 5.99
    },
    {
      "store_number": "037419",
      "name": "Taco Bell",
      "city": "Midland",
      "state": "GA",
      "price": 5.99
    },
    {
      "store_number": "029111",
      "name": "Taco Bell",
      "city": "Birmingham",
      "state": "AL",
      "price": 5.99
    },
    {
      "store_number": "029114",
      "name": "Taco Bell",
      "city": "Tarrant",
      "state": "AL",
      "price": 5.99
    }
  ],
  "min_price_store_numbers": [
    "041154",
    "042584",
    "035455",
    "042128",
    "030177",
    "042488",
    "037008",
    "037419",
    "029111",
    "029114",
    "029153",
    "029144",
    "029717",
    "042823",
    "042572",
    "016335",
    "042828",
    "041800",
    "029085",
    "042825",
    "041801",
    "041802",
    "015360",
    "031394",
    "026432",
    "039946"
  ],
  "priciest_stores": [
    {
      "store_number": "041248",
      "name": "Taco Bell",
      "city": "Douglasville",
      "state": "GA",
      "price": 6.99
    },
    {
      "store_number": "041319",
      "name": "Taco Bell",
      "city": "Canton",
      "state": "GA",
      "price": 6.99
    },
    {
      "store_number": "037038",
      "name": "Taco Bell",
      "city": "Jamestown",
      "state": "TN",
      "price": 6.99
    },
    {
      "store_number": "019292",
      "name": "Taco Bell",
      "city": "Knoxville",
      "state": "TN",
      "price": 6.99
    },
    {
      "store_number": "041488",
      "name": "Taco Bell (ATL Airport)",
      "city": "Atlanta",
      "state": "GA",
      "price": 6.99
    },
    {
      "store_number": "037728",
      "name": "Taco Bell",
      "city": "Kennesaw",
      "state": "GA",
      "price": 6.79
    },
    {
      "store_number": "032055",
      "name": "Taco Bell",
      "city": "Buford",
      "state": "GA",
      "price": 6.79
    },
    {
      "store_number": "038801",
      "name": "Taco Bell",
      "city": "Anniston",
      "state": "AL",
      "price": 6.49
    },
    {
      "store_number": "004431",
      "name": "Taco Bell",
      "city": "Marietta",
      "state": "GA",
      "price": 6.49
    },
    {
      "store_number": "029052",
      "name": "Taco Bell",
      "city": "Sevierville",
      "state": "TN",
      "price": 6.49
    }
  ],
  "price_changes": [
    {
      "store_number": "029007",
      "store_name": "Taco Bell",
      "city": "Chattanooga",
      "state": "TN",
      "change_type": "item_removed",
      "old_price": 5.99,
      "new_price": null,
      "observed_at": "2026-03-23T13:54:54.912621+00:00"
    },
    {
      "store_number": "038801",
      "store_name": "Taco Bell",
      "city": "Anniston",
      "state": "AL",
      "change_type": "item_added",
      "old_price": null,
      "new_price": 6.49,
      "observed_at": "2026-03-23T05:31:58.850345+00:00"
    },
    {
      "store_number": "004431",
      "store_name": "Taco Bell",
      "city": "Marietta",
      "state": "GA",
      "change_type": "item_added",
      "old_price": null,
      "new_price": 6.49,
      "observed_at": "2026-03-23T05:31:05.738361+00:00"
    },
    {
      "store_number": "039946",
      "store_name": "Taco Bell",
      "city": "Monroe",
      "state": "GA",
      "change_type": "item_added",
      "old_price": null,
      "new_price": 5.99,
      "observed_at": "2026-03-23T05:30:43.903205+00:00"
    },
    {
      "store_number": "029052",
      "store_name": "Taco Bell",
      "city": "Sevierville",
      "state": "TN",
      "change_type": "item_added",
      "old_price": null,
      "new_price": 6.49,
      "observed_at": "2026-03-23T05:30:27.224468+00:00"
    },
    {
      "store_number": "026432",
      "store_name": "Taco Bell",
      "city": "Pigeon Forge",
      "state": "TN",
      "change_type": "item_added",
      "old_price": null,
      "new_price": 5.99,
      "observed_at": "2026-03-23T05:29:11.277333+00:00"
    },
    {
      "store_number": "031394",
      "store_name": "Taco Bell",
      "city": "Brewton",
      "state": "AL",
      "change_type": "item_added",
      "old_price": null,
      "new_price": 5.99,
      "observed_at": "2026-03-23T05:29:03.351675+00:00"
    },
    {
      "store_number": "015360",
      "store_name": "Taco Bell",
      "city": "Alcoa",
      "state": "TN",
      "change_type": "item_added",
      "old_price": null,
      "new_price": 5.99,
      "observed_at": "2026-03-23T05:26:39.324703+00:00"
    },
    {
      "store_number": "005623",
      "store_name": "Taco Bell",
      "city": "Marietta",
      "state": "GA",
      "change_type": "item_added",
      "old_price": null,
      "new_price": 6.49,
      "observed_at": "2026-03-23T05:24:16.680106+00:00"
    },
    {
      "store_number": "041802",
      "store_name": "Taco Bell",
      "city": "Athens",
      "state": "GA",
      "change_type": "item_added",
      "old_price": null,
      "new_price": 5.99,
      "observed_at": "2026-03-23T05:22:28.498781+00:00"
    },
    {
      "store_number": "041801",
      "store_name": "Taco Bell",
      "city": "Marietta",
      "state": "GA",
      "change_type": "item_added",
      "old_price": null,
      "new_price": 5.99,
      "observed_at": "2026-03-23T05:12:08.844554+00:00"
    },
    {
      "store_number": "042825",
      "store_name": "Taco Bell",
      "city": "Mobile",
      "state": "AL",
      "change_type": "item_added",
      "old_price": null,
      "new_price": 5.99,
      "observed_at": "2026-03-23T05:10:30.210895+00:00"
    },
    {
      "store_number": "029085",
      "store_name": "Taco Bell",
      "city": "Macon",
      "state": "GA",
      "change_type": "item_added",
      "old_price": null,
      "new_price": 5.99,
      "observed_at": "2026-03-23T05:09:26.733892+00:00"
    },
    {
      "store_number": "041800",
      "store_name": "Taco Bell",
      "city": "Roswell",
      "state": "GA",
      "change_type": "item_added",
      "old_price": null,
      "new_price": 5.99,
      "observed_at": "2026-03-23T05:06:14.128643+00:00"
    },
    {
      "store_number": "042828",
      "store_name": "Taco Bell",
      "city": "Mobile",
      "state": "AL",
      "change_type": "item_added",
      "old_price": null,
      "new_price": 5.99,
      "observed_at": "2026-03-23T05:05:06.776290+00:00"
    },
    {
      "store_number": "041248",
      "store_name": "Taco Bell",
      "city": "Douglasville",
      "state": "GA",
      "change_type": "item_added",
      "old_price": null,
      "new_price": 6.99,
      "observed_at": "2026-03-23T05:02:01.404262+00:00"
    },
    {
      "store_number": "041319",
      "store_name": "Taco Bell",
      "city": "Canton",
      "state": "GA",
      "change_type": "item_added",
      "old_price": null,
      "new_price": 6.99,
      "observed_at": "2026-03-23T05:00:45.776141+00:00"
    },
    {
      "store_number": "029026",
      "store_name": "Taco Bell",
      "city": "Knoxville",
      "state": "TN",
      "change_type": "item_added",
      "old_price": null,
      "new_price": 6.49,
      "observed_at": "2026-03-23T04:58:27.280465+00:00"
    },
    {
      "store_number": "016335",
      "store_name": "Taco Bell",
      "city": "Lenoir City",
      "state": "TN",
      "change_type": "item_added",
      "old_price": null,
      "new_price": 5.99,
      "observed_at": "2026-03-23T04:57:08.826564+00:00"
    },
    {
      "store_number": "042572",
      "store_name": "Taco Bell",
      "city": "Fairburn",
      "state": "GA",
      "change_type": "item_added",
      "old_price": null,
      "new_price": 5.99,
      "observed_at": "2026-03-23T04:02:03.188452+00:00"
    },
    {
      "store_number": "042823",
      "store_name": "Taco Bell",
      "city": "Saraland",
      "state": "AL",
      "change_type": "item_added",
      "old_price": null,
      "new_price": 5.99,
      "observed_at": "2026-03-23T04:01:45.764558+00:00"
    },
    {
      "store_number": "040571",
      "store_name": "Taco Bell",
      "city": "Chattanooga",
      "state": "TN",
      "change_type": "item_added",
      "old_price": null,
      "new_price": 6.49,
      "observed_at": "2026-03-23T04:00:54.123006+00:00"
    },
    {
      "store_number": "029046",
      "store_name": "Taco Bell",
      "city": "Ooltewah",
      "state": "TN",
      "change_type": "item_added",
      "old_price": null,
      "new_price": 6.49,
      "observed_at": "2026-03-23T04:00:40.815214+00:00"
    },
    {
      "store_number": "029717",
      "store_name": "Taco Bell",
      "city": "Tuscaloosa",
      "state": "AL",
      "change_type": "item_added",
      "old_price": null,
      "new_price": 5.99,
      "observed_at": "2026-03-23T04:00:40.183179+00:00"
    },
    {
      "store_number": "029144",
      "store_name": "Taco Bell",
      "city": "Tuscaloosa",
      "state": "AL",
      "change_type": "item_added",
      "old_price": null,
      "new_price": 5.99,
      "observed_at": "2026-03-23T04:00:37.842804+00:00"
    },
    {
      "store_number": "029030",
      "store_name": "Taco Bell",
      "city": "Ringgold",
      "state": "GA",
      "change_type": "item_added",
      "old_price": null,
      "new_price": 6.49,
      "observed_at": "2026-03-23T04:00:26.835043+00:00"
    },
    {
      "store_number": "029007",
      "store_name": "Taco Bell",
      "city": "Chattanooga",
      "state": "TN",
      "change_type": "item_added",
      "old_price": null,
      "new_price": 5.99,
      "observed_at": "2026-03-23T04:00:21.839164+00:00"
    },
    {
      "store_number": "029045",
      "store_name": "Taco Bell",
      "city": "Fort Oglethorpe",
      "state": "GA",
      "change_type": "item_added",
      "old_price": null,
      "new_price": 6.49,
      "observed_at": "2026-03-23T04:00:06.225903+00:00"
    },
    {
      "store_number": "029153",
      "store_name": "Taco Bell",
      "city": "Hoover",
      "state": "AL",
      "change_type": "item_added",
      "old_price": null,
      "new_price": 5.99,
      "observed_at": "2026-03-23T03:59:49.207655+00:00"
    },
    {
      "store_number": "029114",
      "store_name": "Taco Bell",
      "city": "Tarrant",
      "state": "AL",
      "change_type": "item_added",
      "old_price": null,
      "new_price": 5.99,
      "observed_at": "2026-03-23T03:59:48.491404+00:00"
    },
    {
      "store_number": "029027",
      "store_name": "Taco Bell",
      "city": "Dalton",
      "state": "GA",
      "change_type": "item_added",
      "old_price": null,
      "new_price": 6.49,
      "observed_at": "2026-03-23T03:59:36.349627+00:00"
    },
    {
      "store_number": "029111",
      "store_name": "Taco Bell",
      "city": "Birmingham",
      "state": "AL",
      "change_type": "item_added",
      "old_price": null,
      "new_price": 5.99,
      "observed_at": "2026-03-23T03:59:32.448338+00:00"
    },
    {
      "store_number": "037486",
      "store_name": "Taco Bell",
      "city": "Irondale",
      "state": "AL",
      "change_type": "item_added",
      "old_price": null,
      "new_price": 6.49,
      "observed_at": "2026-03-23T03:59:16.073050+00:00"
    },
    {
      "store_number": "037728",
      "store_name": "Taco Bell",
      "city": "Kennesaw",
      "state": "GA",
      "change_type": "item_added",
      "old_price": null,
      "new_price": 6.79,
      "observed_at": "2026-03-23T03:59:08.192554+00:00"
    },
    {
      "store_number": "037419",
      "store_name": "Taco Bell",
      "city": "Midland",
      "state": "GA",
      "change_type": "item_added",
      "old_price": null,
      "new_price": 5.99,
      "observed_at": "2026-03-23T03:59:03.192131+00:00"
    },
    {
      "store_number": "037038",
      "store_name": "Taco Bell",
      "city": "Jamestown",
      "state": "TN",
      "change_type": "item_added",
      "old_price": null,
      "new_price": 6.99,
      "observed_at": "2026-03-23T03:58:57.279632+00:00"
    },
    {
      "store_number": "037008",
      "store_name": "Taco Bell",
      "city": "Hoover",
      "state": "AL",
      "change_type": "item_added",
      "old_price": null,
      "new_price": 5.99,
      "observed_at": "2026-03-23T03:58:56.393393+00:00"
    },
    {
      "store_number": "026342",
      "store_name": "Taco Bell",
      "city": "Lawrenceville",
      "state": "GA",
      "change_type": "item_added",
      "old_price": null,
      "new_price": 6.49,
      "observed_at": "2026-03-23T03:58:46.227513+00:00"
    },
    {
      "store_number": "033295",
      "store_name": "Taco Bell",
      "city": "Cleveland",
      "state": "TN",
      "change_type": "item_added",
      "old_price": null,
      "new_price": 6.49,
      "observed_at": "2026-03-23T03:58:40.137905+00:00"
    },
    {
      "store_number": "042488",
      "store_name": "Taco Bell",
      "city": "Cookeville",
      "state": "TN",
      "change_type": "item_added",
      "old_price": null,
      "new_price": 5.99,
      "observed_at": "2026-03-23T03:58:21.984190+00:00"
    },
    {
      "store_number": "032055",
      "store_name": "Taco Bell",
      "city": "Buford",
      "state": "GA",
      "change_type": "item_added",
      "old_price": null,
      "new_price": 6.79,
      "observed_at": "2026-03-23T03:57:59.595717+00:00"
    },
    {
      "store_number": "030177",
      "store_name": "Taco Bell",
      "city": "Eufaula",
      "state": "AL",
      "change_type": "item_added",
      "old_price": null,
      "new_price": 5.99,
      "observed_at": "2026-03-23T03:57:24.930952+00:00"
    },
    {
      "store_number": "042128",
      "store_name": "Taco Bell",
      "city": "Chipley",
      "state": "FL",
      "change_type": "item_added",
      "old_price": null,
      "new_price": 5.99,
      "observed_at": "2026-03-23T03:57:17.885213+00:00"
    },
    {
      "store_number": "019292",
      "store_name": "Taco Bell",
      "city": "Knoxville",
      "state": "TN",
      "change_type": "item_added",
      "old_price": null,
      "new_price": 6.99,
      "observed_at": "2026-03-23T03:57:08.293944+00:00"
    },
    {
      "store_number": "035455",
      "store_name": "Taco Bell",
      "city": "Pinson",
      "state": "AL",
      "change_type": "item_added",
      "old_price": null,
      "new_price": 5.99,
      "observed_at": "2026-03-23T03:57:04.290047+00:00"
    },
    {
      "store_number": "042584",
      "store_name": "Taco Bell",
      "city": "McDonough",
      "state": "GA",
      "change_type": "item_added",
      "old_price": null,
      "new_price": 5.99,
      "observed_at": "2026-03-23T03:56:20.030419+00:00"
    },
    {
      "store_number": "041488",
      "store_name": "Taco Bell (ATL Airport)",
      "city": "Atlanta",
      "state": "GA",
      "change_type": "item_added",
      "old_price": null,
      "new_price": 6.99,
      "observed_at": "2026-03-23T03:56:07.473641+00:00"
    },
    {
      "store_number": "041154",
      "store_name": "Taco Bell",
      "city": "Columbus",
      "state": "GA",
      "change_type": "item_added",
      "old_price": null,
      "new_price": 5.99,
      "observed_at": "2026-03-23T03:56:06.702421+00:00"
    }
  ],
  "calories_from_menu": 620,
  "map_data": [
    [
      "041154",
      32.473945760941746,
      -84.9882127315456,
      5.99,
      "Taco Bell",
      "Columbus",
      "GA"
    ],
    [
      "042584",
      33.4647,
      -84.2306,
      5.99,
      "Taco Bell",
      "McDonough",
      "GA"
    ],
    [
      "035455",
      33.69690488411811,
      -86.60679751521161,
      5.99,
      "Taco Bell",
      "Pinson",
      "AL"
    ],
    [
      "042128",
      30.759401645916046,
      -85.54742068356954,
      5.99,
      "Taco Bell",
      "Chipley",
      "FL"
    ],
    [
      "030177",
      31.843358589965696,
      -85.16671570107967,
      5.99,
      "Taco Bell",
      "Eufaula",
      "AL"
    ],
    [
      "042488",
      36.17576839999999,
      -85.50415740674515,
      5.99,
      "Taco Bell",
      "Cookeville",
      "TN"
    ],
    [
      "037008",
      33.358462822648114,
      -86.85306624544107,
      5.99,
      "Taco Bell",
      "Hoover",
      "AL"
    ],
    [
      "037419",
      32.53776933341696,
      -84.86787174979743,
      5.99,
      "Taco Bell",
      "Midland",
      "GA"
    ],
    [
      "029111",
      33.55784678574716,
      -86.88956658200459,
      5.99,
      "Taco Bell",
      "Birmingham",
      "AL"
    ],
    [
      "029114",
      33.58550381128001,
      -86.77022203803057,
      5.99,
      "Taco Bell",
      "Tarrant",
      "AL"
    ],
    [
      "029153",
      33.37553645889424,
      -86.80206133982665,
      5.99,
      "Taco Bell",
      "Hoover",
      "AL"
    ],
    [
      "029144",
      33.16753465984693,
      -87.52459099562482,
      5.99,
      "Taco Bell",
      "Tuscaloosa",
      "AL"
    ],
    [
      "029717",
      33.123306055379736,
      -87.55137115716934,
      5.99,
      "Taco Bell",
      "Tuscaloosa",
      "AL"
    ],
    [
      "042823",
      30.802412695504476,
      -88.07241439819336,
      5.99,
      "Taco Bell",
      "Saraland",
      "AL"
    ],
    [
      "042572",
      33.53980644411624,
      -84.57611403902706,
      5.99,
      "Taco Bell",
      "Fairburn",
      "GA"
    ],
    [
      "016335",
      35.810910605655216,
      -84.26391898537986,
      5.99,
      "Taco Bell",
      "Lenoir City",
      "TN"
    ],
    [
      "042828",
      30.72067301787852,
      -88.15761208534241,
      5.99,
      "Taco Bell",
      "Mobile",
      "AL"
    ],
    [
      "041800",
      34.06469727675827,
      -84.42325707593481,
      5.99,
      "Taco Bell",
      "Roswell",
      "GA"
    ],
    [
      "029085",
      32.815355372789554,
      -83.69803921134917,
      5.99,
      "Taco Bell",
      "Macon",
      "GA"
    ],
    [
      "042825",
      30.67554927235233,
      -88.14249698887579,
      5.99,
      "Taco Bell",
      "Mobile",
      "AL"
    ],
    [
      "041801",
      33.94497804839833,
      -84.6247772276729,
      5.99,
      "Taco Bell",
      "Marietta",
      "GA"
    ],
    [
      "041802",
      33.94081012771555,
      -83.45053468646256,
      5.99,
      "Taco Bell",
      "Athens",
      "GA"
    ],
    [
      "015360",
      35.81643031039195,
      -83.98044356707027,
      5.99,
      "Taco Bell",
      "Alcoa",
      "TN"
    ],
    [
      "031394",
      31.141078130371458,
      -87.06821591276761,
      5.99,
      "Taco Bell",
      "Brewton",
      "AL"
    ],
    [
      "026432",
      35.80377693492917,
      -83.58050286769867,
      5.99,
      "Taco Bell",
      "Pigeon Forge",
      "TN"
    ],
    [
      "039946",
      33.79201875090728,
      -83.73402078556178,
      5.99,
      "Taco Bell",
      "Monroe",
      "GA"
    ],
    [
      "033295",
      35.2144,
      -84.8686,
      6.49,
      "Taco Bell",
      "Cleveland",
      "TN"
    ],
    [
      "026342",
      33.980636492251286,
      -84.08123346241287,
      6.49,
      "Taco Bell",
      "Lawrenceville",
      "GA"
    ],
    [
      "037486",
      33.5265,
      -86.6642,
      6.49,
      "Taco Bell",
      "Irondale",
      "AL"
    ],
    [
      "029027",
      34.795373624737906,
      -84.96162227843519,
      6.49,
      "Taco Bell",
      "Dalton",
      "GA"
    ],
    [
      "029045",
      34.938262361554905,
      -85.21441481543206,
      6.49,
      "Taco Bell",
      "Fort Oglethorpe",
      "GA"
    ],
    [
      "029030",
      34.91287467416936,
      -85.12561383813002,
      6.49,
      "Taco Bell",
      "Ringgold",
      "GA"
    ],
    [
      "029046",
      35.08375987197869,
      -85.0627376366737,
      6.49,
      "Taco Bell",
      "Ooltewah",
      "TN"
    ],
    [
      "040571",
      35.06270588603029,
      -85.13815782883033,
      6.49,
      "Taco Bell",
      "Chattanooga",
      "TN"
    ],
    [
      "029026",
      36.07020161616586,
      -83.92685928012295,
      6.49,
      "Taco Bell",
      "Knoxville",
      "TN"
    ],
    [
      "005623",
      34.0366508931735,
      -84.46423148151278,
      6.49,
      "Taco Bell",
      "Marietta",
      "GA"
    ],
    [
      "029052",
      35.90558945648954,
      -83.58061645926682,
      6.49,
      "Taco Bell",
      "Sevierville",
      "TN"
    ],
    [
      "004431",
      33.92456432368397,
      -84.57523492863402,
      6.49,
      "Taco Bell",
      "Marietta",
      "GA"
    ],
    [
      "038801",
      33.7190015,
      -85.81864569999999,
      6.49,
      "Taco Bell",
      "Anniston",
      "AL"
    ],
    [
      "032055",
      34.0647052,
      -83.9841147,
      6.79,
      "Taco Bell",
      "Buford",
      "GA"
    ],
    [
      "037728",
      34.01794478344271,
      -84.56413769853002,
      6.79,
      "Taco Bell",
      "Kennesaw",
      "GA"
    ],
    [
      "041488",
      33.63840238391459,
      -84.42932417361067,
      6.99,
      "Taco Bell (ATL Airport)",
      "Atlanta",
      "GA"
    ],
    [
      "019292",
      36.03309999284835,
      -83.86894236495063,
      6.99,
      "Taco Bell",
      "Knoxville",
      "TN"
    ],
    [
      "037038",
      36.43596602758595,
      -84.93641937395971,
      6.99,
      "Taco Bell",
      "Jamestown",
      "TN"
    ],
    [
      "041319",
      34.17765211148667,
      -84.42180990125053,
      6.99,
      "Taco Bell",
      "Canton",
      "GA"
    ],
    [
      "041248",
      33.71830055882164,
      -84.76882606744766,
      6.99,
      "Taco Bell",
      "Douglasville",
      "GA"
    ]
  ]
}